{
  "id": "algebra-8-16-homework",
  "title": "Домашнє завдання: Тотожність (√a)² = a. Рівняння x² = a",
  "type": "homework",
  "exercises": [
    {
      "id": "16.2",
      "title": "Вправа 16.2",
      "tasks": [
        {
          "id": "1)",
          "q": "Знайдіть значення виразу: \\((\\sqrt{10})^2\\)",
          "a": "10",
          "type": "input"
        },
        {
          "id": "2)",
          "q": "Знайдіть значення виразу: \\((\\sqrt{7.2})^2\\)",
          "a": "7.2",
          "type": "input"
        }
      ]
    },
    {
      "id": "16.4",
      "title": "Вправа 16.4",
      "tasks": [
        {
          "id": "1)",
          "q": "Чи має корені рівняння: \\(x^2 = 36\\)? (так/ні)",
          "a": "так",
          "type": "input"
        },
        {
          "id": "2)",
          "q": "Чи має корені рівняння: \\(x^2 = -5\\)? (так/ні)",
          "a": "ні",
          "type": "input"
        }
      ]
    },
    {
      "id": "16.6",
      "title": "Вправа 16.6",
      "tasks": [
        {
          "id": "1)",
          "q": "Обчисліть: \\((-\\sqrt{13})^2\\)",
          "a": "13",
          "type": "input"
        },
        {
          "id": "2)",
          "q": "Обчисліть: \\(\\sqrt{17} \\cdot \\sqrt{17}\\)",
          "a": "17",
          "type": "input"
        },
        {
          "id": "3)",
          "q": "Обчисліть: \\((3\\sqrt{5})^2\\)",
          "a": "45",
          "type": "input"
        },
        {
          "id": "4)",
          "q": "Обчисліть: \\(\\left(-\\frac{1}{5}\\sqrt{50}\\right)^2\\)",
          "a": "2",
          "type": "input"
        },
        {
          "id": "5)",
          "q": "Обчисліть: \\(-5 \\cdot \\sqrt{2} \\cdot \\sqrt{2}\\)",
          "a": "-10",
          "type": "input"
        },
        {
          "id": "6)",
          "q": "Обчисліть: \\(0.5 \\cdot (-\\sqrt{8})^2\\)",
          "a": "4",
          "type": "input"
        },
        {
          "id": "7)",
          "q": "Обчисліть: \\(\\left(\\frac{1}{\\sqrt{11}}\\right)^2\\)",
          "a": "1/11",
          "type": "input"
        },
        {
          "id": "8)",
          "q": "Обчисліть: \\(\\left(-\\frac{\\sqrt{6}}{5}\\right)^2\\)",
          "a": "6/25",
          "type": "input"
        }
      ]
    },
    {
      "id": "16.8",
      "title": "Вправа 16.8",
      "tasks": [
        {
          "id": "1)",
          "q": "Знайдіть значення виразу: \\(2.5 + (-\\sqrt{9})^2\\)",
          "a": "11.5",
          "type": "input"
        },
        {
          "id": "2)",
          "q": "Знайдіть значення виразу: \\(6 \\left(\\frac{2}{\\sqrt{3}}\\right)^2\\)",
          "a": "8",
          "type": "input"
        },
        {
          "id": "3)",
          "q": "Знайдіть значення виразу: \\(15 : \\left(-\\frac{5}{\\sqrt{3}}\\right)^2\\)",
          "a": "1.8",
          "type": "input"
        },
        {
          "id": "4)",
          "q": "Знайдіть значення виразу: \\(\\frac{1}{20} (\\sqrt{10})^2\\)",
          "a": "0.5",
          "type": "input"
        }
      ]
    },
    {
      "id": "16.10",
      "title": "Вправа 16.10",
      "tasks": [
        {
          "id": "1)",
          "q": "Розв'яжіть рівняння: \\(x^2 = 64\\)",
          "a": "8; -8",
          "type": "input"
        },
        {
          "id": "2)",
          "q": "Розв'яжіть рівняння: \\(x^2 = 0.25\\)",
          "a": "0.5; -0.5",
          "type": "input"
        },
        {
          "id": "3)",
          "q": "Розв'яжіть рівняння: \\(x^2 = 196\\)",
          "a": "14; -14",
          "type": "input"
        },
        {
          "id": "4)",
          "q": "Розв'яжіть рівняння: \\(x^2 = -9\\)",
          "a": "немає",
          "type": "input"
        },
        {
          "id": "5)",
          "q": "Розв'яжіть рівняння: \\(x^2 = 3\\)",
          "a": "r3; -r3",
          "type": "input"
        },
        {
          "id": "6)",
          "q": "Розв'яжіть рівняння: \\(x^2 = \\frac{25}{36}\\)",
          "a": "5/6; -5/6",
          "type": "input"
        }
      ]
    },
    {
      "id": "16.12",
      "title": "Вправа 16.12",
      "tasks": [
        {
          "id": "1)",
          "q": "Розв'яжіть рівняння: \\(x^2 + 0.02 = 0.27\\)",
          "a": "0.5; -0.5",
          "type": "input"
        },
        {
          "id": "2)",
          "q": "Розв'яжіть рівняння: \\(x^2 - 18 = 7\\)",
          "a": "5; -5",
          "type": "input"
        },
        {
          "id": "3)",
          "q": "Розв'яжіть рівняння: \\(21 - x^2 = 0\\)",
          "a": "r21; -r21",
          "type": "input"
        },
        {
          "id": "4)",
          "q": "Розв'яжіть рівняння: \\(-\\frac{1}{3}x^2 = 3\\)",
          "a": "немає",
          "type": "input"
        }
      ]
    },
    {
      "id": "16.16",
      "title": "Вправа 16.16",
      "tasks": [
        {
          "id": "1)",
          "q": "Обчисліть: \\(((-\\sqrt{5})^2)^2\\)",
          "a": "25",
          "type": "input"
        },
        {
          "id": "2)",
          "q": "Обчисліть: \\((4\\sqrt{5})^2 - (5\\sqrt{4})^2\\)",
          "a": "-20",
          "type": "input"
        },
        {
          "id": "3)",
          "q": "Обчисліть: \\(25 \\cdot \\left(-\\frac{1}{5}\\sqrt{3}\\right)^2 + \\frac{1}{4}(2\\sqrt{5})^2\\)",
          "a": "8",
          "type": "input"
        },
        {
          "id": "4)",
          "q": "Обчисліть: \\(\\sqrt{10.89} - \\left(\\frac{1}{2}\\sqrt{12}\\right)^2\\)",
          "a": "0.3",
          "type": "input"
        },
        {
          "id": "5)",
          "q": "Обчисліть: \\((3\\sqrt{2})^2 - 3 \\cdot (-\\sqrt{2})^2\\)",
          "a": "12",
          "type": "input"
        },
        {
          "id": "6)",
          "q": "Обчисліть: \\(\\left(\\frac{2}{5}\\sqrt{15}\\right)^2 + \\left(-\\frac{3}{4}\\sqrt{8}\\right)^2\\)",
          "a": "6.9",
          "type": "input"
        }
      ]
    },
    {
      "id": "16.18",
      "title": "Вправа 16.18",
      "tasks": [
        {
          "id": "1)",
          "q": "Розв'яжіть рівняння: \\((x + 2)^2 = 25\\)",
          "a": "3; -7",
          "type": "input"
        },
        {
          "id": "2)",
          "q": "Розв'яжіть рівняння: \\((y - 3)^2 = 16\\)",
          "a": "7; -1",
          "type": "input"
        },
        {
          "id": "3)",
          "q": "Розв'яжіть рівняння: \\((m + 1)^2 = 0\\)",
          "a": "-1",
          "type": "input"
        },
        {
          "id": "4)",
          "q": "Розв'яжіть рівняння: \\((x - 4)^2 = 2\\)",
          "a": "4+r2; 4-r2",
          "type": "input"
        },
        {
          "id": "5)",
          "q": "Розв'яжіть рівняння: \\(\\left(y - \\frac{1}{5}\\right)^2 = \\frac{4}{25}\\)",
          "a": "0.6; -0.2",
          "type": "input"
        },
        {
          "id": "6)",
          "q": "Розв'яжіть рівняння: \\((m - 5)^2 = -9\\)",
          "a": "немає",
          "type": "input"
        }
      ]
    },
    {
      "id": "16.21",
      "title": "Вправа 16.21",
      "tasks": [
        {
          "id": "1)",
          "q": "Розв'яжіть рівняння: \\(\\frac{x-3}{4} = \\frac{5}{x+3}\\)",
          "a": "r29; -r29",
          "type": "input"
        },
        {
          "id": "2)",
          "q": "Розв'яжіть рівняння: \\((3x + 2)^2 + (3x - 2)^2 = 26\\)",
          "a": "1; -1",
          "type": "input"
        }
      ]
    },
    {
      "id": "16.23",
      "title": "Вправа 16.23",
      "tasks": [
        {
          "id": "1)",
          "q": "Знайдіть корені рівняння: \\(\\sqrt{4} + \\sqrt{x^2 + 5} = 5\\)",
          "a": "2; -2",
          "type": "input"
        },
        {
          "id": "2)",
          "q": "Знайдіть корені рівняння: \\(3|x^2 - 1| + 2 = 14\\)",
          "a": "r5; -r5",
          "type": "input"
        }
      ]
    }
  ],
  "repetition": [],
  "prep": []
}
